mathtoolspy/__init__.py
mathtoolspy/distribution/__init__.py
mathtoolspy/distribution/normal_distribution.py
mathtoolspy/integration/__init__.py
mathtoolspy/integration/gauss_kronrod_integrator.py
mathtoolspy/integration/gauss_legendre_integrator.py
mathtoolspy/integration/gauss_lobatto_integrator.py
mathtoolspy/integration/simplex_integrator.py
mathtoolspy/interpolation/__init__.py
mathtoolspy/interpolation/bilinear.py
mathtoolspy/interpolation/linear.py
mathtoolspy/interpolation/spline.py
mathtoolspy/matrix/__init__.py
mathtoolspy/matrix/misc.py
mathtoolspy/solver/__init__.py
mathtoolspy/solver/analytic_solver.py
mathtoolspy/solver/minimize_algorithm_1dim_brent.py
mathtoolspy/solver/minimize_algorithm_1dim_golden.py
mathtoolspy/solver/minimize_algorithm_ndim_powell.py
mathtoolspy/solver/minimum_bracketing.py
mathtoolspy/solver/optimizer.py
mathtoolspy/utils/__init__.py
mathtoolspy/utils/math_fcts.py
mathtoolspy/utils/mathconst.py
mathtoolspy/utils/surface.py
mathtoolspy-0.3.dist-info/LICENSE
mathtoolspy-0.3.dist-info/METADATA
mathtoolspy-0.3.dist-info/WHEEL
mathtoolspy-0.3.dist-info/top_level.txt
mathtoolspy-0.3.dist-info/RECORD
